nabg/__init__.py
nabg/__main__.py
nabg/bullshit_generator.py
nabg/default_patterns.py
nabg/default_vocabulary.py
nabg/errors.py
nabg-1.0.2.dist-info/LICENSE.txt
nabg-1.0.2.dist-info/METADATA
nabg-1.0.2.dist-info/WHEEL
nabg-1.0.2.dist-info/entry_points.txt
nabg-1.0.2.dist-info/top_level.txt
nabg-1.0.2.dist-info/RECORD
