Metadata-Version: 2.1
Name: nabg
Version: 1.0.2
Summary: A customizable bullshit generator based on Seb Pearce's 'New-Age Bullshit Generator'
Home-page: https://github.com/naveen-u/nabg
Author: Naveen Unnikrishnan
Author-email: naveenunnikrishnan98@gmail.com
License: UNKNOWN
Platform: UNKNOWN
Classifier: Programming Language :: Python :: 3
Classifier: Programming Language :: Python :: 3 :: Only
Classifier: Programming Language :: Python :: 3.8
Classifier: License :: OSI Approved :: MIT License
Classifier: Operating System :: OS Independent
Classifier: Typing :: Typed
Requires-Dist: click (>7.0)
Provides-Extra: dev
Requires-Dist: pytest (>=6.2.2) ; extra == 'dev'
